README.md
ez_setup.py
setup.py
sc_drv/__init__.py
sc_drv/method.py
sc_drv/normtests.py
sc_drv/plot.py
sc_drv/tests.py
sc_drv.egg-info/PKG-INFO
sc_drv.egg-info/SOURCES.txt
sc_drv.egg-info/dependency_links.txt
sc_drv.egg-info/requires.txt
sc_drv.egg-info/top_level.txt
sc_drv/libs/__init__.py
sc_drv/libs/heatmap.py