Metadata-Version: 1.1
Name: sc-drv
Version: 0.2.1
Summary: DRV processes: Group Decision Making.
Home-page: https://github.com/leliel12/sc_drv
Author: Cabral, Luczywo & Zanazzi
Author-email: jbc.develop@gmail.com
License: 3 Clause BSD
Keywords: mcda,mcdm,group-decision-making,muti-criteria
Platform: UNKNOWN
Classifier: Intended Audience :: Science/Research
Classifier: Intended Audience :: Developers
Classifier: License :: OSI Approved
Classifier: Programming Language :: Python
Classifier: Topic :: Software Development
Classifier: Topic :: Scientific/Engineering
Classifier: Operating System :: Microsoft :: Windows
Classifier: Operating System :: POSIX
Classifier: Operating System :: Unix
Classifier: Operating System :: MacOS
Classifier: Programming Language :: Python :: 3
Classifier: Programming Language :: Python :: 3.4
Classifier: Programming Language :: Python :: 3.5
Classifier: Programming Language :: Python :: 3.6
